{"is_source_file": true, "format": "JavaScript", "description": "Test script for Cypress end-to-end testing framework, verifying the Teams RBAC page UI.", "external_files": ["cypress/e2e/commands.js", "cypress/support/index.js", "cypress/plugins/index.js"], "external_methods": ["cy.visit", "cy.contains"], "published": [], "classes": [], "methods": [{"name": "it", "description": "Defines a test case for Cypress testing framework."}, {"name": "cy.visit", "description": "Navigates to the specified URL."}, {"name": "cy.contains", "description": "Finds DOM elements containing specific text."}], "calls": ["cy.visit", "cy.contains"], "search-terms": ["Teams RBAC", "cypress", "e2e tests", "teams page"], "state": 2, "file_id": 47, "knowledge_revision": 104, "git_revision": "", "ctags": [], "hash": "cfc2914c6f31b842c83cad9fe8aa2c02", "format-version": 4, "code-base-name": "UnifiedCloudResourceManagerApp", "filename": "UnifiedCloudResourceManagerApp/cypress/e2e/teams_rbac.cy.js", "revision_history": [{"104": ""}]}